delg/__init__.py
delg/client.py
delg/config.py
delg/datum_io.py
delg/delf_config_pb2.py
delg/docker_runner.py
delg/extractor.py
delg/feature_extractor.py
delg/model_weights.py
delg/similarity.py
delg/utils.py
delg/model_configs/config_global.pbtxt
delg/model_configs/config_local.pbtxt
delg-0.1.1.dist-info/licenses/LICENSE
delg-0.1.1.dist-info/METADATA
delg-0.1.1.dist-info/WHEEL
delg-0.1.1.dist-info/top_level.txt
delg-0.1.1.dist-info/RECORD
