Metadata-Version: 2.4
Name: delg
Version: 0.1.1
Summary: delg: A Python Package for Dockerized DELG Implementation
Author-email: Duje Giljanović <giljanovic.duje@gmail.com>
License:                                  Apache License
License-File: LICENSE
Requires-Dist: requests>=2.24.0
Requires-Dist: scikit-learn>=0.24
Requires-Dist: scipy>=1.5
Requires-Dist: numpy>=1.19.0
Requires-Dist: scikit-image>=0.18.0
Provides-Extra: server
Requires-Dist: fastapi; extra == "server"
Requires-Dist: uvicorn; extra == "server"
Requires-Dist: tensorflow-cpu; extra == "server"
Requires-Dist: pillow; extra == "server"
Requires-Dist: numpy; extra == "server"
Requires-Dist: protobuf; extra == "server"
Dynamic: license-file
